YetAnotherPicSearch/__init__.py
YetAnotherPicSearch/ascii2d.py
YetAnotherPicSearch/baidu.py
YetAnotherPicSearch/config.py
YetAnotherPicSearch/ehentai.py
YetAnotherPicSearch/google.py
YetAnotherPicSearch/iqdb.py
YetAnotherPicSearch/nhentai.py
YetAnotherPicSearch/nhentai_model.py
YetAnotherPicSearch/saucenao.py
YetAnotherPicSearch/utils.py
YetAnotherPicSearch/whatanime.py
YetAnotherPicSearch/yandex.py
yetanotherpicsearchmigang-0.0.1.dist-info/LICENSE
yetanotherpicsearchmigang-0.0.1.dist-info/METADATA
yetanotherpicsearchmigang-0.0.1.dist-info/WHEEL
yetanotherpicsearchmigang-0.0.1.dist-info/RECORD
