Metadata-Version: 2.1
Name: YetAnotherPicSearchMigang
Version: 0.0.1
Summary: Yet Another Picture Search Nonebot Plugin
Home-page: https://github.com/NekoAria/YetAnotherPicSearch
License: GPL-3.0-only
Keywords: nonebot,ascii2d,baidu,e-hentai,google,iqdb,saucenao,tracemoe,yandex,anime,danbooru,doujin,pixiv
Author: NekoAria
Requires-Python: >=3.8,<4
Classifier: License :: OSI Approved :: GNU General Public License v3 (GPLv3)
Classifier: Programming Language :: Python :: 3
Classifier: Programming Language :: Python :: 3.8
Classifier: Programming Language :: Python :: 3.9
Classifier: Programming Language :: Python :: 3.10
Classifier: Programming Language :: Python :: 3.11
Classifier: Programming Language :: Python :: 3.12
Provides-Extra: socks
Requires-Dist: PicImageSearch (>=3.9.7,<4.0.0)
Requires-Dist: arrow (>=1.3.0,<2.0.0)
Requires-Dist: cachetools (>=5.3.2,<6.0.0)
Requires-Dist: httpx (>=0.25.2,<0.26.0)
Requires-Dist: lxml (>=4.9.3,<5.0.0)
Requires-Dist: nonebot-adapter-onebot (>=2.4.1,<3.0.0)
Requires-Dist: nonebot2 (>=2.2.0,<3.0.0)
Requires-Dist: pyquery (>=2.0.0,<3.0.0)
Requires-Dist: python-socks[asyncio] (>=2.4.4,<3.0.0) ; extra == "socks"
Requires-Dist: shelved-cache (>=0.3.1,<0.4.0)
Requires-Dist: socksio (>=1.0.0,<2.0.0) ; extra == "socks"
Requires-Dist: tenacity (>=8.2.3,<9.0.0)
Project-URL: Repository, https://github.com/NekoAria/YetAnotherPicSearch
